prunepytest-0.6.5.dist-info/METADATA
prunepytest-0.6.5.dist-info/WHEEL
prunepytest-0.6.5.dist-info/entry_points.txt
prunepytest/api.py
prunepytest/args.py
prunepytest/defaults.py
prunepytest/graph.py
prunepytest/py.typed
prunepytest/pytest/plugin.py
prunepytest/pytest/selector.py
prunepytest/pytest/util.py
prunepytest/pytest/validator.py
prunepytest/pytest/__init__.py
prunepytest/tracker.py
prunepytest/util.py
prunepytest/validator.py
prunepytest/vcs/detect.py
prunepytest/vcs/git.py
prunepytest/vcs/__init__.py
prunepytest/_prunepytest.pyi
prunepytest/__init__.py
prunepytest/__main__.py
prunepytest/_prunepytest.pyd
prunepytest-0.6.5.dist-info/RECORD
