Metadata-Version: 2.4
Name: prunepytest
Version: 0.6.5
Classifier: Programming Language :: Rust
Classifier: Programming Language :: Python :: 3.7
Classifier: Programming Language :: Python :: Implementation :: CPython
Classifier: Development Status :: 4 - Beta
Classifier: Environment :: Console
Classifier: Framework :: Pytest
Classifier: Intended Audience :: Developers
Classifier: Topic :: Software Development :: Build Tools
Classifier: Topic :: Software Development :: Libraries :: Python Modules
Classifier: Topic :: Software Development :: Testing
Summary: only test relevant files
Home-Page: https://github.com/prunepytest/prunepytest
Author-email: Hugues Bruant <hugues@betakappaphi.com>
Requires-Python: >=3.7
Project-URL: Homepage, https://github.com/taste-prune-pie/prune-py-test
Project-URL: Respository, https://github.com/taste-prune-pie/prune-py-test.git
Project-URL: Issues, https://github.com/taste-prune-pie/prune-py-test/issues
